initPygame/__init__.py
initPygame/core.py
initpygame-0.2.dist-info/METADATA
initpygame-0.2.dist-info/WHEEL
initpygame-0.2.dist-info/entry_points.txt
initpygame-0.2.dist-info/top_level.txt
initpygame-0.2.dist-info/RECORD
